sqspipeline/__init__.py
sqspipeline/pipelines.py
scrapy_sqspipeline-1.0.0.dist-info/LICENSE
scrapy_sqspipeline-1.0.0.dist-info/METADATA
scrapy_sqspipeline-1.0.0.dist-info/WHEEL
scrapy_sqspipeline-1.0.0.dist-info/top_level.txt
scrapy_sqspipeline-1.0.0.dist-info/RECORD
