Metadata-Version: 2.1
Name: scrapy-sqspipeline
Version: 1.0.0
Summary: UNKNOWN
Home-page: https://github.com/d-yoshi/scrapy-sqspipeline
Author: d-yoshi
Author-email: keisuke.yoshida.job@gmail.com
License: MIT
Keywords: scrapy pipeline aws sqs
Platform: UNKNOWN
Classifier: Programming Language :: Python :: 3
Classifier: Programming Language :: Python :: 3.5
Classifier: Programming Language :: Python :: 3.6
Classifier: Programming Language :: Python :: 3.7
Classifier: Framework :: Scrapy
Classifier: License :: OSI Approved :: MIT License
Requires-Dist: Scrapy (>=1.1)
Requires-Dist: boto3
